captioned_image_dataset_loader/__init__.py
captioned_image_dataset_loader/captioned_image_dataset_generator.py
captioned_image_dataset_loader-1.0.2.dist-info/METADATA
captioned_image_dataset_loader-1.0.2.dist-info/WHEEL
captioned_image_dataset_loader-1.0.2.dist-info/RECORD
