Metadata-Version: 2.4
Name: captioned-image-dataset-loader
Version: 1.0.2
Summary: Flexible dataset tool for creating a 🤗 Datasets dataset from image-caption pairs.
Author: Alex Senden
License: MIT
Requires-Python: >=3.8
Requires-Dist: datasets==4.0.0
Requires-Dist: pillow==11.3.0
